dh.py
simple_dh-1.0.0.dist-info/METADATA
simple_dh-1.0.0.dist-info/WHEEL
simple_dh-1.0.0.dist-info/top_level.txt
simple_dh-1.0.0.dist-info/RECORD
