Metadata-Version: 2.1
Name: simple-dh
Version: 1.0.0
Summary: Simple Animation Maker
Home-page: https://github.com/none-None1/simple_dh
Author: None1
Keywords: animation
Requires-Dist: opencv-python
Requires-Dist: imageio
